errcode/__init__.py
errcode/data/23.csv
errcode/data/__init__.py
errcode/data/qnd.csv
errcode/tests/__init__.py
errcode-0.1.0.dist-info/METADATA
errcode-0.1.0.dist-info/WHEEL
errcode-0.1.0.dist-info/top_level.txt
errcode-0.1.0.dist-info/RECORD
