Metadata-Version: 2.1
Name: errcode
Version: 0.1.0
Summary: Error Detecting/Correcting Codes
Home-page: http://github.com/zhiqingxiao/errcode/
Author: Zhiqing Xiao
Author-email: xzq.xiaozhiqing@gmail.com
Classifier: Programming Language :: Python
Classifier: Intended Audience :: Science/Research
